sstgame/__init__.py
sstgame/__main__.py
sstgame/anagram.py
sstgame/anagram.txt
sstgame/hangman.py
sstgame/hangman.txt
sstgame/madlib.py
sstgame/madlib.txt
sstgame/numberGuess.py
sstgame/randomGame.py
sstgame/wyr.py
sstgame/wyr.txt
sstgame-0.2.7.dist-info/LICENSE
sstgame-0.2.7.dist-info/METADATA
sstgame-0.2.7.dist-info/WHEEL
sstgame-0.2.7.dist-info/entry_points.txt
sstgame-0.2.7.dist-info/top_level.txt
sstgame-0.2.7.dist-info/RECORD
